text_cleaner/__init__.py
text_cleaner/text_cleaner.py
text_cleaner_yuvan-0.1.0.dist-info/METADATA
text_cleaner_yuvan-0.1.0.dist-info/WHEEL
text_cleaner_yuvan-0.1.0.dist-info/top_level.txt
text_cleaner_yuvan-0.1.0.dist-info/RECORD
